ppc_asm/__init__.py
ppc_asm/dol_file.py
ppc_asm/py.typed
ppc_asm/version.py
ppc_asm/assembler/__init__.py
ppc_asm/assembler/custom_ppc.py
ppc_asm/assembler/ppc.py
ppc_asm-1.6.0.dist-info/licenses/LICENSE
ppc_asm-1.6.0.dist-info/METADATA
ppc_asm-1.6.0.dist-info/WHEEL
ppc_asm-1.6.0.dist-info/top_level.txt
ppc_asm-1.6.0.dist-info/RECORD
